waxtablet/__init__.py
waxtablet/notebook_lsp.py
waxtablet/types.py
waxtablet-0.2.3.dist-info/METADATA
waxtablet-0.2.3.dist-info/WHEEL
waxtablet-0.2.3.dist-info/licenses/LICENSE
waxtablet-0.2.3.dist-info/RECORD
