Metadata-Version: 2.4
Name: waxtablet
Version: 0.2.3
Summary: Auto-diffing LSP client for remote Jupyter notebooks.
Author-email: Eric Zhang <ekzhang1@gmail.com>
License-File: LICENSE
Requires-Python: >=3.9
